csirtg_dnsdb/__init__.py
csirtg_dnsdb/_version.py
csirtg_dnsdb/client.py
csirtg_dnsdb/exceptions.py
csirtg_dnsdb-0.0.0a4.dist-info/DESCRIPTION.rst
csirtg_dnsdb-0.0.0a4.dist-info/METADATA
csirtg_dnsdb-0.0.0a4.dist-info/RECORD
csirtg_dnsdb-0.0.0a4.dist-info/WHEEL
csirtg_dnsdb-0.0.0a4.dist-info/entry_points.txt
csirtg_dnsdb-0.0.0a4.dist-info/metadata.json
csirtg_dnsdb-0.0.0a4.dist-info/top_level.txt
test/__init__.py
test/test_client.py
